{
  "version": 1,
  "type": "standardized_logistic_regression",
  "task": "stage2_pure_fat_classifier",
  "featureExtractor": "logmel_summary",
  "sampleRate": 16000,
  "clipSamples": 8000,
  "classes": [
    "fat",
    "pure"
  ],
  "positiveClass": "pure",
  "negativeClass": "fat",
  "confidenceThreshold": 0.6,
  "features": [
    "logmel_total_mean",
    "logmel_total_std",
    "logmel_total_max",
    "logmel_total_peak_pos",
    "logmel_total_impact_delta",
    "logmel_total_tail_delta",
    "mel_00_mean",
    "mel_00_std",
    "mel_00_max",
    "mel_00_impact_delta",
    "mel_00_tail_delta",
    "mel_01_mean",
    "mel_01_std",
    "mel_01_max",
    "mel_01_impact_delta",
    "mel_01_tail_delta",
    "mel_02_mean",
    "mel_02_std",
    "mel_02_max",
    "mel_02_impact_delta",
    "mel_02_tail_delta",
    "mel_03_mean",
    "mel_03_std",
    "mel_03_max",
    "mel_03_impact_delta",
    "mel_03_tail_delta",
    "mel_04_mean",
    "mel_04_std",
    "mel_04_max",
    "mel_04_impact_delta",
    "mel_04_tail_delta",
    "mel_05_mean",
    "mel_05_std",
    "mel_05_max",
    "mel_05_impact_delta",
    "mel_05_tail_delta",
    "mel_06_mean",
    "mel_06_std",
    "mel_06_max",
    "mel_06_impact_delta",
    "mel_06_tail_delta",
    "mel_07_mean",
    "mel_07_std",
    "mel_07_max",
    "mel_07_impact_delta",
    "mel_07_tail_delta",
    "mel_08_mean",
    "mel_08_std",
    "mel_08_max",
    "mel_08_impact_delta",
    "mel_08_tail_delta",
    "mel_09_mean",
    "mel_09_std",
    "mel_09_max",
    "mel_09_impact_delta",
    "mel_09_tail_delta",
    "mel_10_mean",
    "mel_10_std",
    "mel_10_max",
    "mel_10_impact_delta",
    "mel_10_tail_delta",
    "mel_11_mean",
    "mel_11_std",
    "mel_11_max",
    "mel_11_impact_delta",
    "mel_11_tail_delta",
    "mel_12_mean",
    "mel_12_std",
    "mel_12_max",
    "mel_12_impact_delta",
    "mel_12_tail_delta",
    "mel_13_mean",
    "mel_13_std",
    "mel_13_max",
    "mel_13_impact_delta",
    "mel_13_tail_delta",
    "mel_14_mean",
    "mel_14_std",
    "mel_14_max",
    "mel_14_impact_delta",
    "mel_14_tail_delta",
    "mel_15_mean",
    "mel_15_std",
    "mel_15_max",
    "mel_15_impact_delta",
    "mel_15_tail_delta",
    "mel_16_mean",
    "mel_16_std",
    "mel_16_max",
    "mel_16_impact_delta",
    "mel_16_tail_delta",
    "mel_17_mean",
    "mel_17_std",
    "mel_17_max",
    "mel_17_impact_delta",
    "mel_17_tail_delta",
    "mel_18_mean",
    "mel_18_std",
    "mel_18_max",
    "mel_18_impact_delta",
    "mel_18_tail_delta",
    "mel_19_mean",
    "mel_19_std",
    "mel_19_max",
    "mel_19_impact_delta",
    "mel_19_tail_delta",
    "mel_20_mean",
    "mel_20_std",
    "mel_20_max",
    "mel_20_impact_delta",
    "mel_20_tail_delta",
    "mel_21_mean",
    "mel_21_std",
    "mel_21_max",
    "mel_21_impact_delta",
    "mel_21_tail_delta",
    "mel_22_mean",
    "mel_22_std",
    "mel_22_max",
    "mel_22_impact_delta",
    "mel_22_tail_delta",
    "mel_23_mean",
    "mel_23_std",
    "mel_23_max",
    "mel_23_impact_delta",
    "mel_23_tail_delta",
    "mel_24_mean",
    "mel_24_std",
    "mel_24_max",
    "mel_24_impact_delta",
    "mel_24_tail_delta",
    "mel_25_mean",
    "mel_25_std",
    "mel_25_max",
    "mel_25_impact_delta",
    "mel_25_tail_delta",
    "mel_26_mean",
    "mel_26_std",
    "mel_26_max",
    "mel_26_impact_delta",
    "mel_26_tail_delta",
    "mel_27_mean",
    "mel_27_std",
    "mel_27_max",
    "mel_27_impact_delta",
    "mel_27_tail_delta",
    "mel_28_mean",
    "mel_28_std",
    "mel_28_max",
    "mel_28_impact_delta",
    "mel_28_tail_delta",
    "mel_29_mean",
    "mel_29_std",
    "mel_29_max",
    "mel_29_impact_delta",
    "mel_29_tail_delta",
    "mel_30_mean",
    "mel_30_std",
    "mel_30_max",
    "mel_30_impact_delta",
    "mel_30_tail_delta",
    "mel_31_mean",
    "mel_31_std",
    "mel_31_max",
    "mel_31_impact_delta",
    "mel_31_tail_delta",
    "mel_32_mean",
    "mel_32_std",
    "mel_32_max",
    "mel_32_impact_delta",
    "mel_32_tail_delta",
    "mel_33_mean",
    "mel_33_std",
    "mel_33_max",
    "mel_33_impact_delta",
    "mel_33_tail_delta",
    "mel_34_mean",
    "mel_34_std",
    "mel_34_max",
    "mel_34_impact_delta",
    "mel_34_tail_delta",
    "mel_35_mean",
    "mel_35_std",
    "mel_35_max",
    "mel_35_impact_delta",
    "mel_35_tail_delta",
    "mel_36_mean",
    "mel_36_std",
    "mel_36_max",
    "mel_36_impact_delta",
    "mel_36_tail_delta",
    "mel_37_mean",
    "mel_37_std",
    "mel_37_max",
    "mel_37_impact_delta",
    "mel_37_tail_delta",
    "mel_38_mean",
    "mel_38_std",
    "mel_38_max",
    "mel_38_impact_delta",
    "mel_38_tail_delta",
    "mel_39_mean",
    "mel_39_std",
    "mel_39_max",
    "mel_39_impact_delta",
    "mel_39_tail_delta"
  ],
  "mean": [
    -7.549707175019725,
    1.6641776101747265,
    -3.493571718154646,
    0.18784029038112526,
    2.686182886422039,
    -3.4640359988981797,
    -10.021812532821857,
    1.5726634952971743,
    -6.275411360023465,
    3.32736942562022,
    -1.6128808972067001,
    -10.080365947294764,
    2.151902612599649,
    -5.5374814046891245,
    4.848828016498224,
    -3.345056083508319,
    -10.919379976293166,
    2.1612337748474175,
    -6.283126908631585,
    4.593476794271631,
    -4.061119167165142,
    -12.040110317210726,
    1.932499370016584,
    -7.460133806355073,
    3.293879386349881,
    -3.913722267291912,
    -12.74641313707987,
    2.138852783700747,
    -7.582460366468393,
    3.234418608674215,
    -4.698508994914983,
    -13.231523022040362,
    2.111994534222818,
    -8.277994356758583,
    1.9857638832233486,
    -4.458413005859923,
    -13.487386934779044,
    2.1379558107031675,
    -8.875309411475701,
    0.6149424975182984,
    -4.118749929195227,
    -13.620714494388725,
    2.279131475669527,
    -8.468785862052284,
    -0.15492812365004202,
    -3.7669817866692044,
    -13.800546650178,
    2.4578701906384426,
    -7.166333228740149,
    -0.2288124587622347,
    -3.1971658979500894,
    -13.999164708002551,
    2.403910271633689,
    -6.895783708815202,
    0.40176623178323767,
    -3.1185809128070474,
    -14.219941540517437,
    1.9382590618503912,
    -8.344968107828167,
    0.2511536218844639,
    -2.2668555857957347,
    -14.253958108134304,
    1.5790388802914779,
    -9.506359089324702,
    0.10515437856044435,
    -1.5580955631904958,
    -14.257780344057347,
    1.4937749324188063,
    -9.85109022220836,
    0.14522808439507434,
    -1.3945594374789774,
    -14.380777683962116,
    1.5804339158550516,
    -9.644774986028985,
    0.09648138898320574,
    -1.566818954686049,
    -14.529740218013535,
    1.7048500837465208,
    -9.19398897390731,
    0.17112091770481178,
    -1.7089276123873485,
    -14.592585434599142,
    1.8047196035759923,
    -8.839539745128127,
    0.5612395288251193,
    -1.8450190586385593,
    -14.855137798613447,
    1.7779929989413072,
    -8.909285811475545,
    1.0019131321456456,
    -2.1534982772940534,
    -15.232561459971166,
    1.741151935978037,
    -9.316152285178424,
    1.3613426431400988,
    -2.409353524998474,
    -15.524093787538504,
    1.7582665052152644,
    -9.554964093398041,
    1.4404866320599503,
    -2.5775029477860225,
    -15.67830807179031,
    1.810211908807517,
    -9.20138396551041,
    1.2638491009948194,
    -2.5285289532506985,
    -15.807981113623729,
    1.8515213496778677,
    -9.069298265973767,
    1.1866484138880942,
    -2.5144872769238633,
    -15.981767118324735,
    1.8236474904903779,
    -9.109802444555498,
    1.2151283119801892,
    -2.354726091655151,
    -16.303375375633152,
    1.790489297762944,
    -9.525455407152595,
    1.0794058922988234,
    -2.249717623454808,
    -16.479488707513735,
    1.6636109115130755,
    -10.269465377874994,
    0.9447122236608084,
    -1.9314454136263202,
    -16.53293313141654,
    1.4568928143431852,
    -11.161765744205876,
    0.7042307485229644,
    -1.3058532670378746,
    -16.48529712737879,
    1.4668172569269071,
    -10.935843076013894,
    0.5584509873483154,
    -1.0982253699505138,
    -16.27649306061345,
    1.5951267289083073,
    -10.267412984770761,
    0.48054141696076297,
    -1.2091979010975418,
    -16.105699717394348,
    1.802207155645419,
    -9.421158036945773,
    0.33308536455792886,
    -1.4669109869680104,
    -16.25648625412497,
    1.9058891188159137,
    -8.975847653419043,
    0.6723712565897761,
    -1.8833024734383672,
    -16.512902975388105,
    1.8566511792577085,
    -9.1957949343429,
    1.16240083957836,
    -1.8850556299912367,
    -16.846378260650805,
    1.655126083506302,
    -10.107443869175132,
    1.2076731009152222,
    -1.5718704562355061,
    -17.105512585056818,
    1.6361702655832835,
    -10.246151356705266,
    1.3575008179275736,
    -1.6268551690589375,
    -17.310676096206933,
    1.5883093936381243,
    -10.530209138034317,
    1.4662019729071318,
    -1.659294134066199,
    -17.450557667993277,
    1.564380930947873,
    -10.894443803523707,
    1.5349937544294157,
    -1.8885959813248951,
    -17.523251791922245,
    1.6139068865587685,
    -10.918200483206634,
    1.767052896010767,
    -2.1782978034302127,
    -17.644984963368543,
    1.4524628812280822,
    -11.637984567170795,
    1.4115422406247726,
    -1.9470261375130427,
    -17.717467609015966,
    1.4644120253113537,
    -11.536338839795137,
    1.350268788089641,
    -1.9665343740341938,
    -17.735633386656378,
    1.4332274535992355,
    -11.642660723298091,
    1.1857455755451394,
    -1.9020129343886794,
    -17.744843132165794,
    1.3708905173551185,
    -11.888271493596347,
    0.8998656409899658,
    -1.7253697199927895,
    -17.85776711767675,
    1.2362243513014202,
    -12.449641754055138,
    0.8138639792563453,
    -1.549906808688221
  ],
  "std": [
    0.7114114916795938,
    0.18175810746955612,
    0.4869990388829219,
    0.02291276087647383,
    0.9217125790118846,
    0.6558650167836446,
    0.8708261904725252,
    0.3577579681711774,
    0.944361023652764,
    1.4533888376776554,
    0.7233269003722621,
    1.0262331706457866,
    0.397744135989387,
    1.14284003544989,
    1.4322202296000601,
    0.9331659566649041,
    0.9577486692722086,
    0.49399536634319124,
    1.2579449697069025,
    1.4936772786289296,
    1.1562938591226724,
    0.7856808048699807,
    0.46789262338304516,
    1.6168529290229743,
    1.444644905347482,
    1.3823611558190378,
    0.6378331021045585,
    0.5256078198462971,
    1.6618760426558459,
    1.265216328657077,
    1.4773098347932625,
    0.39584120996649136,
    0.4538961885707154,
    1.2857971515571485,
    1.181575081518446,
    1.3064746073648934,
    0.3966424761057249,
    0.2603654387455189,
    0.8984971848256187,
    1.1609034693212117,
    0.7706906894094774,
    0.37451474645659083,
    0.28333620240190555,
    0.6872735153982911,
    1.1761882103774044,
    0.8452086636832623,
    0.3847990512495021,
    0.2879139022039495,
    0.6943756388812826,
    1.1055083420893717,
    0.9084228710601968,
    0.2604350015318236,
    0.25892965176326216,
    1.2815235484495722,
    0.8714931839013326,
    0.7973301924512771,
    0.31720574494113957,
    0.2972037388773411,
    1.5146161150391306,
    0.8057317549376279,
    0.8245182850682804,
    0.2981829166656573,
    0.23172990937155086,
    1.1554378700417118,
    0.739178324139798,
    0.842001203037993,
    0.318883247377303,
    0.24253503858201242,
    1.190931269001692,
    0.8152134216546186,
    0.8409783818896156,
    0.29877360604485687,
    0.2916114071100275,
    1.435804565351319,
    0.9078504171114726,
    0.9020521055867718,
    0.30873764757814626,
    0.22457046487705928,
    1.067188121531851,
    0.8955769949716893,
    0.9125428697833431,
    0.37852730759490916,
    0.16986776117536154,
    0.8820860164393359,
    0.817305570615956,
    0.8867098668255786,
    0.309863678467353,
    0.2474729055224764,
    1.0603992968326106,
    0.9768956790974745,
    0.96267713363039,
    0.3160763340208581,
    0.20688390747011157,
    0.7832410334766016,
    0.8405950056437442,
    0.7738593854860256,
    0.3142678436663141,
    0.1941147254439249,
    0.7962731021179026,
    0.8464148355243845,
    0.7002646813615548,
    0.2607888282340061,
    0.18985672454129246,
    0.7659357516964663,
    0.7297958843649007,
    0.6631254847289701,
    0.27020577445509847,
    0.14402042904932147,
    0.5133104849175948,
    0.8021378750053996,
    0.6588111766431057,
    0.22255701928138236,
    0.12154483359534196,
    0.5457566277448637,
    0.6670515940043299,
    0.5712269052769472,
    0.23134738746255196,
    0.09391093766682083,
    0.491611104722794,
    0.7200278341596473,
    0.5218829156912578,
    0.2855494074045042,
    0.08340727403133877,
    0.2942516443780141,
    0.7807453889925208,
    0.5307486883131898,
    0.2760780865864862,
    0.0808022362964523,
    0.4735236454104835,
    0.7679965109727993,
    0.5366465845249841,
    0.285120373081107,
    0.09660218973868975,
    0.4322196971034995,
    0.7280486346488795,
    0.4376849373145884,
    0.3010327920776641,
    0.10350626966258444,
    0.5139313844867865,
    0.6846002932993906,
    0.5258723742041802,
    0.3055207547507546,
    0.13294419673978566,
    0.7007828270572856,
    0.9252787803934585,
    0.5748199657585777,
    0.2862403969903847,
    0.1780757417063961,
    0.9443302429640081,
    0.8951320173065427,
    0.638546690058291,
    0.2650029592709343,
    0.12506237517530236,
    0.610843862615757,
    0.7606142831310877,
    0.5319238246265782,
    0.22437713629714678,
    0.0993116873280671,
    0.456571120023355,
    0.5863331122124982,
    0.4692385246183369,
    0.2138507470401633,
    0.15486110095469136,
    0.7319126941169919,
    0.5814691180311115,
    0.43550356687606556,
    0.1709666127298171,
    0.13833431234859023,
    0.5823305048326655,
    0.6618796212566679,
    0.40113406150535424,
    0.12284680417570122,
    0.15806112470202,
    0.6870030535303423,
    0.6711204158645998,
    0.36190304687691766,
    0.11513750580182311,
    0.176462791101931,
    0.7726349654481312,
    0.6402347932816818,
    0.4122600174959813,
    0.11268167164526777,
    0.21762074838460801,
    0.7910842239852139,
    0.5928289815679819,
    0.4825648683401702,
    0.12741695470764192,
    0.2693435095373904,
    1.0283714064237377,
    0.6372356249441504,
    0.5301388575839859,
    0.10924165060525429,
    0.24918373128017296,
    1.0355014136735783,
    0.6472128350852752,
    0.4993953235065779,
    0.06747934329398622,
    0.20009874575202583,
    0.939601724033675,
    0.5044720538171826,
    0.3598784178198422,
    0.0743334861695578,
    0.23130599179411032,
    1.0840704757694686,
    0.4795212485207852,
    0.3711990393454945
  ],
  "weights": [
    -0.054556288263710485,
    0.02499040079293524,
    0.008287541650664509,
    -0.059361258237045,
    -0.05238295599735247,
    -0.008456202055149591,
    -0.056667073659020975,
    0.0014251005591298048,
    0.049408676392417715,
    -0.050837880043452445,
    -0.07149192271582021,
    -0.0484777226932125,
    0.016285201555148617,
    0.03048399802394856,
    -0.056461461429296526,
    -0.04023182163625094,
    -0.04570486801661696,
    0.006634256776774816,
    0.010019540947646094,
    -0.035291439687742523,
    -0.004099346270043208,
    -0.07214261985472215,
    -0.0542286584063337,
    -0.06980503628157547,
    -0.08001265972968899,
    0.06424796161980251,
    -0.1310315309487735,
    -0.1352298760731817,
    -0.1436907485279861,
    -0.11650344793778736,
    0.13486330903522412,
    -0.12012101459372526,
    -0.1357516353637579,
    -0.13601246002621445,
    -0.0961002836418417,
    0.14367962789232394,
    -0.0009191749546872911,
    -0.09231765963295294,
    -0.09095308753357853,
    -0.01371372933528653,
    0.07605806032748502,
    0.02598444368427661,
    -0.062012592468187376,
    -0.055666006510077325,
    -0.011646662771911133,
    0.05865068829888691,
    0.028793900817155303,
    -0.024227895829792425,
    0.021314337860345513,
    -0.05860384908867129,
    0.055915283698058,
    0.02519851174918548,
    -0.0038781297463440067,
    0.010921300157943858,
    -0.015041774409094131,
    -0.009916177801978326,
    0.017711985614407875,
    -0.020444206804689228,
    -0.013268400726591219,
    -0.023017323665248158,
    0.019139803662060386,
    0.00711636716125437,
    -0.012560035928911945,
    -0.06374878652362814,
    0.036011546789727636,
    -0.010896808991292554,
    -0.013692763251865846,
    -0.055192768563218454,
    -0.08112978606817109,
    0.04790409520106525,
    -0.02728092473481798,
    0.0228729531409445,
    -0.05229002211280736,
    -0.08340999982020825,
    0.017445363623786618,
    0.004664791066588731,
    0.026844562347191982,
    -0.02712199410691218,
    -0.07789494945829492,
    0.051334091317010326,
    0.0099947117653218,
    0.03743304399373597,
    0.006061918552321142,
    -0.058697246573299555,
    -0.007348049255478594,
    0.020410625588862915,
    0.03935750058218921,
    -0.04712073982375053,
    -0.06270206131298996,
    -0.01893707281780052,
    0.02494912861029547,
    0.027342549098958037,
    0.017112443721444666,
    -0.0019227361787040964,
    0.03842154777441897,
    -0.016403666286318435,
    0.055474614142041946,
    -0.023092864809830915,
    -0.09238978522875091,
    0.03421453095074053,
    -0.00011288249929516448,
    0.012078299152221927,
    -0.06989367242456804,
    -0.09206079039490984,
    0.0014481591230431814,
    0.04327060546094888,
    0.05634189641888809,
    -0.0550227318357991,
    -0.039041908467818534,
    -0.005652367745879295,
    0.053444388976011836,
    0.0604116031380163,
    -0.050839213715699355,
    -0.09681035172294336,
    0.02202399982634099,
    -0.002213158207237295,
    0.03855725224703094,
    -0.0371613362180865,
    -0.045403445210660934,
    -0.011728021518465389,
    -0.006508652589056443,
    0.07660354215937581,
    0.048594184931344854,
    0.07239362651369316,
    0.05504784632256123,
    -0.018123529338207732,
    0.045706840163139174,
    -0.004727169081770244,
    0.03949065281102063,
    0.06697390177360749,
    -0.010565661405696288,
    0.03172417817969573,
    0.08345405875950644,
    0.12265155240035255,
    0.07800509676737495,
    -0.05201476352603526,
    0.04031354005191649,
    -0.049073078297654005,
    -0.04276690494390782,
    0.011283572126302975,
    0.0301596614737139,
    0.05987100527973859,
    0.05646886203750508,
    0.06014578451275644,
    0.04387482976922698,
    -0.007657509467695505,
    0.06723242988119002,
    0.05316128874356079,
    0.07023789176896698,
    0.057371202359592276,
    -0.01127032291536793,
    0.041846893255285476,
    0.07487027964096031,
    0.0889970385400148,
    0.003825803217069737,
    0.011406503672667606,
    0.033866694270154554,
    0.002080240762879524,
    0.01495817164909428,
    -0.0028574511086470354,
    0.08428941834245311,
    0.013621515303174105,
    -0.049145819317932354,
    -0.047552123360465874,
    0.0367665764135316,
    0.06883072793365135,
    0.013862606064558157,
    -0.012221208714245441,
    -0.02214676532770813,
    0.061149243306978886,
    -0.00972371534212965,
    0.03888735881713264,
    0.028598527106262813,
    -0.007271196861701474,
    0.04836639215271246,
    -0.057069699034085264,
    -0.012675657756909977,
    -0.050351615802944075,
    -0.052163746309331356,
    0.006191727356171567,
    0.018805009241929915,
    -0.003493620115798087,
    -0.02807665663649985,
    -0.03110416038138489,
    -0.0011616227216389116,
    0.019777797236973326,
    -0.057910290976436594,
    -0.08178106824087089,
    -0.09480471185760432,
    -0.032317034544890426,
    0.05975111984004465,
    -0.04017385027641166,
    -0.05731628714982138,
    -0.06657613712632418,
    -0.007404986200191951,
    0.029315609117716773,
    -0.07375178632790577,
    -0.07174142009081487,
    -0.08809212811631044,
    0.004400961748705079,
    0.04059520334891523,
    -0.11871093908630583,
    -0.12228318105683222,
    -0.13212607924948927,
    -0.04520907101396963,
    0.09332858615206044
  ],
  "bias": 0.05647864414745775,
  "training": {
    "generatedAt": "2026-04-23T23:50:43.135Z",
    "pure": 10,
    "fat": 9,
    "excluded": 9,
    "excludedPolicy": "manual bad-data exclusions plus topped and 1mm/borderline exclusions for pure-vs-fat v0",
    "exclusionPolicy": {
      "path": "data/stage2_pure_fat_exclusions.json",
      "version": 1,
      "updatedAt": "2026-04-23",
      "manualExclusions": [
        {
          "shotNumber": "49",
          "reason": "bad_data_excluded_by_visual_review"
        },
        {
          "shotNumber": "67",
          "reason": "bad_data_excluded_by_visual_review"
        },
        {
          "shotNumber": "83",
          "reason": "bad_data_excluded_by_visual_review"
        }
      ],
      "builtInReasons": [
        "topped_not_in_pure_vs_fat_v0",
        "borderline_fat_excluded",
        "unknown_folder_label",
        "missing_label_entry"
      ]
    },
    "preparedManifest": "data/stage1b_prepared/manifest.jsonl",
    "cv": {
      "threshold": 0.5,
      "tpPure": 10,
      "fpPure": 2,
      "tnFat": 7,
      "fnPure": 0,
      "accuracy": 0.8947368421052632,
      "purePrecision": 0.8333333333333334,
      "pureRecall": 1,
      "fatPrecision": 1,
      "fatRecall": 0.7777777777777778
    },
    "cvAtConfidence060": {
      "confidenceThreshold": 0.6,
      "unsure": 1,
      "coverage": 0.9473684210526315,
      "kept": {
        "threshold": 0.5,
        "tpPure": 10,
        "fpPure": 1,
        "tnFat": 7,
        "fnPure": 0,
        "accuracy": 0.9444444444444444,
        "purePrecision": 0.9090909090909091,
        "pureRecall": 1,
        "fatPrecision": 1,
        "fatRecall": 0.875
      }
    },
    "oofScoreSeparation": {
      "minPureP": 0.6976594365532632,
      "maxFatP": 0.6393110002789965,
      "separationMargin": 0.05834843627426678,
      "pureScores": [
        0.6976594365532632,
        0.7479120352396452,
        0.8475764364277715,
        0.9324611457579237,
        0.9529342830742198,
        0.9660430627801988,
        0.970317033293678,
        0.9761819862900406,
        0.981602752960639,
        0.9995217751180682
      ],
      "fatScores": [
        0.0006791398048153396,
        0.0027637296801528233,
        0.003035631692940019,
        0.010952622565677127,
        0.02016130123476541,
        0.07666607098729615,
        0.08043734952096533,
        0.5207418148212132,
        0.6393110002789965
      ]
    },
    "trainOnlyMetrics": {
      "threshold": 0.5,
      "tpPure": 10,
      "fpPure": 0,
      "tnFat": 9,
      "fnPure": 0,
      "accuracy": 1,
      "purePrecision": 1,
      "pureRecall": 1,
      "fatPrecision": 1,
      "fatRecall": 1
    },
    "trainScoreSeparation": {
      "minPureP": 0.924236909541573,
      "maxFatP": 0.06974625156362821,
      "separationMargin": 0.8544906579779448,
      "pureScores": [
        0.924236909541573,
        0.9689260270550042,
        0.9731151152349726,
        0.9735561568085136,
        0.9757656480860764,
        0.9764074741514197,
        0.9849324897325826,
        0.9887082281446775,
        0.9895663725075624,
        0.9991501374964457
      ],
      "fatScores": [
        0.0016059634645591526,
        0.0030393590146348516,
        0.0042027680323764045,
        0.009052889912816026,
        0.015366469565232735,
        0.018661698938941734,
        0.020943684146971963,
        0.0568509989833196,
        0.06974625156362821
      ]
    }
  }
}